src/components/memory/generic_rom.vhd

-- =======================================================================================================
--
--  Descrição de Hardware (VHDL) de uma Read Only Memory (ROM) - "Memória de Programa"
--
--  ->> AUTOR: André Solano F. R. Maiolini
--  ->> DATA: 23/06/2024
--
--   ██████╗  ██████╗ ███╗   ███╗
--   ██╔══██╗██╔═══██╗████╗ ████║
--   ██████╔╝██║   ██║██╔████╔██║
--   ██╔══██╗██║   ██║██║╚██╔╝██║
--   ██║  ██║╚██████╔╝██║ ╚═╝ ██║
--   ╚═╝  ╚═╝ ╚═════╝ ╚═╝     ╚═╝
--
--  ->> Diagrama de bloco (entradas e saídas) ============================================================
--
--                    _________
--           addr >--|         |--> data_out
--       CS (LOW) >--|   ROM   |
--       OE (LOW) >--|_________|
--                
-- =======================================================================================================

--| Libraries |-------------------------------------------------------------------------------------------

library ieee;
use ieee.std_logic_1164.all;
use ieee.numeric_std.all;

--| ROM |-------------------------------------------------------------------------------------------------

entity generic_rom is

    generic (
        n      : integer := 8;                                 -- Quantidade de bits de endereçamento
        word   : integer := 16                                 -- Tamanho da palavra de memória
    );

    port (
        cs       : in std_logic;                               -- Chip Selection (CS) ativo em LOW
        oe       : in std_logic;                               -- Output Enable (OE) ativo em LOW
        address  : in std_logic_vector(n-1 downto 0);          -- Barramento de endereço
        data_out : out std_logic_vector(word-1 downto 0)       -- Saída de dados
    );
    
end entity generic_rom;

--| Lógica |----------------------------------------------------------------------------------------------

architecture main of generic_rom is

    -- (PROGRAMA DE TESTE) ------------------------------------------------------------------------------

    -- Nesta seção estão os programas de teste para as funcionalidades e operações do BIP-1.

    type memory_type is array (0 to 2**n - 1) of std_logic_vector(word-1 downto 0);

    -- Gravação do código a ser executado pela CPU:

    -- Teste: "Cálculo de 5! (fatorial de 5)"

    constant memory : memory_type := (                                                                                                                                                            
        0  => x"3001",   -- 0 : 3001                                                                                                                                                              
        1  => x"1000",   -- 1 : 1000
        2  => x"3005",   -- 2 : 3005
        3  => x"1001",   -- 3 : 1001
        4  => x"3000",   -- 4 : 3000
        5  => x"1006",   -- 5 : 1006
        6  => x"2001",   -- 6 : 2001
        7  => x"A006",   -- 7 : A006
        8  => x"B00A",   -- 8 : B00A
        9  => x"8022",   -- 9 : 8022
        10 => x"2001",   -- A : 2001
        11 => x"1002",   -- B : 1002
        12 => x"2000",   -- C : 2000
        13 => x"1003",   -- D : 1003
        14 => x"8015",   -- E : 8015
        15 => x"2004",   -- F : 2004
        16 => x"1000",   -- 10 : 1000
        17 => x"2001",   -- 11 : 2001
        18 => x"7001",   -- 12 : 7001
        19 => x"1001",   -- 13 : 1001
        20 => x"8006",   -- 14 : 8006
        21 => x"3000",   -- 15 : 3000
        22 => x"1004",   -- 16 : 1004
        23 => x"3000",   -- 17 : 3000
        24 => x"1005",   -- 18 : 1005
        25 => x"2004",   -- 19 : 2004
        26 => x"4003",   -- 1A : 4003
        27 => x"1004",   -- 1B : 1004
        28 => x"2002",   -- 1C : 2002
        29 => x"7001",   -- 1D : 7001
        30 => x"1002",   -- 1E : 1002
        31 => x"A005",   -- 1F : A005
        32 => x"B019",   -- 20 : B019
        33 => x"800F",   -- 21 : 800F
        34 => x"2000",   -- 22 : 2000
        35 => x"0000",   -- 23 : 0000
        others => x"0000"
    );

begin

    process (address, cs, oe)
    begin

        if cs = '0' then      -- CS ativo (nível lógico LOW)

            if oe = '0' then  -- OE ativo (nível lógico LOW)

                data_out <= memory(to_integer(unsigned(address)));

            else

                data_out <= (others => 'Z');  -- Alta impedância quando OE não está ativo

            end if;

        else

            data_out <= (others => 'Z');      -- Alta impedância quando CS não está ativo
            
        end if;

    end process;

end architecture main;

-- =======================================================================================================

src/components/counter/generic_counter.vhd
-- Descrição de Hardware (VHDL) de um Contador Genérico de n bits
--
--                  __________
--          clk >--|          |
--                 | Contador |--> count (n bits) 
--           MR >--|__________|
--
--
-- AUTOR: André Solano F. R. Maiolini
-- DATA: 23/06/2024

--| Libraries |------------------------------------------------------------------------------

library ieee;
use ieee.std_logic_1164.all;
use ieee.numeric_std.all;

--| Contador |--------------------------------------------------------------------------------

entity generic_counter is
    generic(n : integer := 4); -- quantidade de bits do contador
    port (
        clk    : in  std_logic;
        MR     : in  std_logic;
        count  : out std_logic_vector(n - 1 downto 0)
    );
end entity generic_counter;

--| Lógica |----------------------------------------------------------------------------------

architecture main of generic_counter is

    signal count_temp : unsigned(n-1 downto 0);

begin

    contagem : process(clk, MR) 
    begin

        if MR = '0' then

            count_temp <= (others => '0');

        elsif falling_edge(clk) then

            count_temp <= count_temp + 1;

        end if;

    end process contagem;

    count <= std_logic_vector(count_temp);

end architecture main;

src/components/timer/generic_timer.vhd
-- Descrição de Hardware (VHDL) de um Timer de Freq. Genérica (MHz)
--
--             _________
--            |         |
--      en >--|  Timer  |--> clk
--            |_________|
--
--
-- AUTOR: André Solano F. R. Maiolini
-- DATA: 23/06/2024

--| Libraries |------------------------------------------------------------------------------

library ieee;
use ieee.std_logic_1164.all;
use ieee.numeric_std.all;

--| Timer |----------------------------------------------------------------------------------

entity generic_timer is

    generic(
        clk_freq : integer := 4
    );

    port(
        clk : out std_logic;
        enable : in std_logic
    );

end entity generic_timer;

--| Lógica |----------------------------------------------------------------------------------

architecture main of generic_timer is
begin

    clock_generator : process
    begin
        
        clk <= '0';
        wait for (1000 ns / clk_freq);
        
        while enable = '1' loop
            clk <= not clk;
            wait for (1000 ns / clk_freq);
        end loop;

        wait;

    end process;

end architecture main;

src/cpu.vhd
--| Libraries |------------------------------------------------------------------------------
library ieee;
use ieee.std_logic_1164.all;
use ieee.numeric_std.all;

--| CPU |------------------------------------------------------------------------------------

entity cpu is

    -- Define genericamente os valores que serão fornecidos pelo arquivo de testes:

    generic(
        n        : integer := 16;                -- Tamanho em bits do PC
        f        : integer := 2000;              -- MHz (freq. clock)
        addr_rom : integer := 16;                -- Bits de endereçamento ROM (instruções)
        i_word   : integer := 16                 -- Tamanho da palavra de instrução
    );

    -- Define as portas da CPU - entradas, saídas e tipos básicos:

    port(
        enable      : in  std_logic;                          -- Enable (ativo em HIGH)
        MR          : in  std_logic;                          -- Master-Reset (ativo em LOW)
        pc_count    : out std_logic_vector(n-1 downto 0);     -- Program Counter (PC)
        instruction : out std_logic_vector(i_word-1 downto 0) -- Leitura da ROM - instrução
    );

end entity cpu;

--| Lógica |----------------------------------------------------------------------------------

architecture main of cpu is

    -- Definindo sinais internos à CPU:

    signal internal_clk : std_logic;                         -- Clock interno da CPU (recebe o clock do TIMER)
    --signal instruction  : std_logic_vector(i_word-1 to 0);   -- Define a instrução que será carregada no IR

    -- Definindo os componentes internos da CPU:

        -- Temporizador genérico:

        component generic_timer is
            generic(
                clk_freq : integer := f      -- Define a frequência do temporizador
            );
            port(
                clk : out std_logic := '0';
                enable : in std_logic
            );
        end component generic_timer;

        -- Contador genérico:

        component generic_counter is
            generic(
                n : integer := n                          -- Define a largura de bits do contador
            );
            port (
                clk    : in  std_logic;
                MR     : in  std_logic;
                count  : out std_logic_vector(n - 1 downto 0)
            );
        end component generic_counter;

        -- Read Only Memory:

        component generic_rom is

            generic (
                n      : integer := addr_rom;   -- Quantidade de bits de endereçamento
                word   : integer := i_word      -- Tamanho da palavra de memória
            );

            port (
                cs       : in std_logic;                               -- Chip Selection (CS) ativo em LOW
                oe       : in std_logic;                               -- Output Enable (OE) ativo em LOW
                address  : in std_logic_vector(n-1 downto 0);          -- Barramento de endereço
                data_out : out std_logic_vector(word-1 downto 0)       -- Saída de dados
            );

        end component generic_rom;

begin

    -- Instância o relógio interno da CPU: TIMER

    TIMER: generic_timer 
        port map(
            internal_clk,                    -- Recebe, a partir do TIMER o internal_clock
            enable                           -- Sinal para habilitar o TIMER interno da CPU
        );

    -- Instância o circuito Program Counter: PC_counter

    PC_counter: generic_counter
        port map(
            internal_clk,                    -- Atribui o clock interno da CPU para o contador
            MR,                              -- Sinal de Master-Reset do PC_counter
            pc_count                         -- Direciona o valor do PC para pc_count
        );

    -- Instância a memória de programa: ROM

    ROM: generic_rom
        port map(
            '0',
            '0',
            pc_count,
            instruction
        );

end architecture main;

----------------------------------------------------------------------------------------------

test/testbench/cpu_tb.vhd
-- Arquivo de testes (testbench) para a CPU (BIP I)

--| Libraries |----------------------------------------------------------------------------------------------------------

library ieee;
use ieee.std_logic_1164.all;

--| Entidade |-----------------------------------------------------------------------------------------------------------

entity cpu_tb is
end entity cpu_tb;

--| Lógica - Testbench |-------------------------------------------------------------------------------------------------

architecture teste of cpu_tb is
  
  -- Definições básicas do processador:

  constant n        : integer := 16;                        -- Tamanho do Program Counter (PC) da CPU em bits
  constant f        : integer := 2000;                      -- Frequência de operação do Timer Interno (MHz)
  constant i_word   : integer := 16;                        -- Palavra de instrução em bits
  constant addr_rom : integer := 16;                        -- Bits de endereçamento da ROM
  
  -- Sinais sendo rastreados:

  signal enable   : std_logic := '1';                       -- Enable (ativo em HIGH)
  signal MR       : std_logic;                              -- Master-Reset (ativo em LOW)
  signal pc_count : std_logic_vector(n-1 downto 0);         -- Program Count
  signal instruct : std_logic_vector(i_word-1 downto 0);    -- Instrução lida da ROM

  -- Declaração do componente CPU:

  component cpu is

    generic(
        n        : integer := n;
        f        : integer := f;
        addr_rom : integer := addr_rom;
        i_word   : integer := i_word
    );

    port(
        enable      : in  std_logic;                          -- Enable (ativo em HIGH)
        MR          : in  std_logic;                          -- Master-Reset (ativo em LOW)
        pc_count    : out std_logic_vector(n-1 downto 0);     -- Program Count
        instruction : out std_logic_vector(i_word-1 downto 0) -- Leitura da ROM - instrução
    );

  end component cpu;

begin

    -- Instanciando o BIP (do tipo cpu) e declarando as portas:

    BIP: cpu port map (enable, MR, pc_count, instruct);

    -- Testando o Program Counter (PC) do BIP:

    test: process
    begin

        MR <= '0';
        wait for 1 ns;
        MR <= '1';
        wait for 7 ns;
        MR <= '0';
        wait for 1 ns;
        MR <= '1';
        wait for 30 ns;
        enable <= '0';

        wait;

    end process test;

end architecture teste;

test/waveform/cpu_tb.vcd
$date
  Sun Jun 23 21:41:58 2024
$end
$version
  GHDL v0
$end
$timescale
  1 fs
$end
$scope module standard $end
$upscope $end
$scope module textio $end
$upscope $end
$scope module std_logic_1164 $end
$upscope $end
$scope module numeric_std $end
$upscope $end
$scope module cpu_tb $end
$var reg 1 ! enable $end
$var reg 1 " mr $end
$var reg 16 # pc_count[15:0] $end
$var reg 16 $ instruct[15:0] $end
$scope module bip $end
$var reg 1 % enable $end
$var reg 1 & mr $end
$var reg 16 ' pc_count[15:0] $end
$var reg 16 ( instruction[15:0] $end
$var reg 1 ) internal_clk $end
$scope module timer $end
$var reg 1 * clk $end
$var reg 1 + enable $end
$upscope $end
$scope module pc_counter $end
$var reg 1 , clk $end
$var reg 1 - mr $end
$var reg 16 . count[15:0] $end
$var reg 16 / count_temp[15:0] $end
$upscope $end
$scope module rom $end
$var reg 1 0 cs $end
$var reg 1 1 oe $end
$var reg 16 2 address[15:0] $end
$var reg 16 3 data_out[15:0] $end
$upscope $end
$upscope $end
$upscope $end
$enddefinitions $end
#0
1!
0"
b0000000000000000 #
b1010101010101010 $
1%
0&
b0000000000000000 '
b1010101010101010 (
1)
1*
1+
1,
0-
b0000000000000000 .
b0000000000000000 /
00
01
b0000000000000000 2
b1010101010101010 3
#500000
0)
0*
0,
#1000000
1"
1&
1)
1*
1,
1-
#1500000
b0000000000000001 #
b1011101110111011 $
b0000000000000001 '
b1011101110111011 (
0)
0*
0,
b0000000000000001 .
b0000000000000001 /
b0000000000000001 2
b1011101110111011 3
#2000000
1)
1*
1,
#2500000
b0000000000000010 #
b1100110011001100 $
b0000000000000010 '
b1100110011001100 (
0)
0*
0,
b0000000000000010 .
b0000000000000010 /
b0000000000000010 2
b1100110011001100 3
#3000000
1)
1*
1,
#3500000
b0000000000000011 #
b1101110111011101 $
b0000000000000011 '
b1101110111011101 (
0)
0*
0,
b0000000000000011 .
b0000000000000011 /
b0000000000000011 2
b1101110111011101 3
#4000000
1)
1*
1,
#4500000
b0000000000000100 #
b0000000000000000 $
b0000000000000100 '
b0000000000000000 (
0)
0*
0,
b0000000000000100 .
b0000000000000100 /
b0000000000000100 2
b0000000000000000 3
#5000000
1)
1*
1,
#5500000
b0000000000000101 #
b0000000000000101 '
0)
0*
0,
b0000000000000101 .
b0000000000000101 /
b0000000000000101 2
#6000000
1)
1*
1,
#6500000
b0000000000000110 #
b0000000000000110 '
0)
0*
0,
b0000000000000110 .
b0000000000000110 /
b0000000000000110 2
#7000000
1)
1*
1,
#7500000
b0000000000000111 #
b0000000000000111 '
0)
0*
0,
b0000000000000111 .
b0000000000000111 /
b0000000000000111 2
#8000000
0"
b0000000000000000 #
b1010101010101010 $
0&
b0000000000000000 '
b1010101010101010 (
1)
1*
1,
0-
b0000000000000000 .
b0000000000000000 /
b0000000000000000 2
b1010101010101010 3
#8500000
0)
0*
0,
#9000000
1"
1&
1)
1*
1,
1-
#9500000
b0000000000000001 #
b1011101110111011 $
b0000000000000001 '
b1011101110111011 (
0)
0*
0,
b0000000000000001 .
b0000000000000001 /
b0000000000000001 2
b1011101110111011 3
#10000000
1)
1*
1,
#10500000
b0000000000000010 #
b1100110011001100 $
b0000000000000010 '
b1100110011001100 (
0)
0*
0,
b0000000000000010 .
b0000000000000010 /
b0000000000000010 2
b1100110011001100 3
#11000000
1)
1*
1,
#11500000
b0000000000000011 #
b1101110111011101 $
b0000000000000011 '
b1101110111011101 (
0)
0*
0,
b0000000000000011 .
b0000000000000011 /
b0000000000000011 2
b1101110111011101 3
#12000000
1)
1*
1,
#12500000
b0000000000000100 #
b0000000000000000 $
b0000000000000100 '
b0000000000000000 (
0)
0*
0,
b0000000000000100 .
b0000000000000100 /
b0000000000000100 2
b0000000000000000 3
#13000000
1)
1*
1,
#13500000
b0000000000000101 #
b0000000000000101 '
0)
0*
0,
b0000000000000101 .
b0000000000000101 /
b0000000000000101 2
#14000000
1)
1*
1,
#14500000
b0000000000000110 #
b0000000000000110 '
0)
0*
0,
b0000000000000110 .
b0000000000000110 /
b0000000000000110 2
#15000000
1)
1*
1,
#15500000
b0000000000000111 #
b0000000000000111 '
0)
0*
0,
b0000000000000111 .
b0000000000000111 /
b0000000000000111 2
#16000000
1)
1*
1,
#16500000
b0000000000001000 #
b0000000000001000 '
0)
0*
0,
b0000000000001000 .
b0000000000001000 /
b0000000000001000 2
#17000000
1)
1*
1,
#17500000
b0000000000001001 #
b0000000000001001 '
0)
0*
0,
b0000000000001001 .
b0000000000001001 /
b0000000000001001 2
#18000000
1)
1*
1,
#18500000
b0000000000001010 #
b0000000000001010 '
0)
0*
0,
b0000000000001010 .
b0000000000001010 /
b0000000000001010 2
#19000000
1)
1*
1,
#19500000
b0000000000001011 #
b0000000000001011 '
0)
0*
0,
b0000000000001011 .
b0000000000001011 /
b0000000000001011 2
#20000000
1)
1*
1,
#20500000
b0000000000001100 #
b0000000000001100 '
0)
0*
0,
b0000000000001100 .
b0000000000001100 /
b0000000000001100 2
#21000000
1)
1*
1,
#21500000
b0000000000001101 #
b0000000000001101 '
0)
0*
0,
b0000000000001101 .
b0000000000001101 /
b0000000000001101 2
#22000000
1)
1*
1,
#22500000
b0000000000001110 #
b0000000000001110 '
0)
0*
0,
b0000000000001110 .
b0000000000001110 /
b0000000000001110 2
#23000000
1)
1*
1,
#23500000
b0000000000001111 #
b0000000000001111 '
0)
0*
0,
b0000000000001111 .
b0000000000001111 /
b0000000000001111 2
#24000000
1)
1*
1,
#24500000
b0000000000010000 #
b0000000000010000 '
0)
0*
0,
b0000000000010000 .
b0000000000010000 /
b0000000000010000 2
#25000000
1)
1*
1,
#25500000
b0000000000010001 #
b0000000000010001 '
0)
0*
0,
b0000000000010001 .
b0000000000010001 /
b0000000000010001 2
#26000000
1)
1*
1,
#26500000
b0000000000010010 #
b0000000000010010 '
0)
0*
0,
b0000000000010010 .
b0000000000010010 /
b0000000000010010 2
#27000000
1)
1*
1,
#27500000
b0000000000010011 #
b0000000000010011 '
0)
0*
0,
b0000000000010011 .
b0000000000010011 /
b0000000000010011 2
#28000000
1)
1*
1,
#28500000
b0000000000010100 #
b0000000000010100 '
0)
0*
0,
b0000000000010100 .
b0000000000010100 /
b0000000000010100 2
#29000000
1)
1*
1,
#29500000
b0000000000010101 #
b0000000000010101 '
0)
0*
0,
b0000000000010101 .
b0000000000010101 /
b0000000000010101 2
#30000000
1)
1*
1,
#30500000
b0000000000010110 #
b0000000000010110 '
0)
0*
0,
b0000000000010110 .
b0000000000010110 /
b0000000000010110 2
#31000000
1)
1*
1,
#31500000
b0000000000010111 #
b0000000000010111 '
0)
0*
0,
b0000000000010111 .
b0000000000010111 /
b0000000000010111 2
#32000000
1)
1*
1,
#32500000
b0000000000011000 #
b0000000000011000 '
0)
0*
0,
b0000000000011000 .
b0000000000011000 /
b0000000000011000 2
#33000000
1)
1*
1,
#33500000
b0000000000011001 #
b0000000000011001 '
0)
0*
0,
b0000000000011001 .
b0000000000011001 /
b0000000000011001 2
#34000000
1)
1*
1,
#34500000
b0000000000011010 #
b0000000000011010 '
0)
0*
0,
b0000000000011010 .
b0000000000011010 /
b0000000000011010 2
#35000000
1)
1*
1,
#35500000
b0000000000011011 #
b0000000000011011 '
0)
0*
0,
b0000000000011011 .
b0000000000011011 /
b0000000000011011 2
#36000000
1)
1*
1,
#36500000
b0000000000011100 #
b0000000000011100 '
0)
0*
0,
b0000000000011100 .
b0000000000011100 /
b0000000000011100 2
#37000000
1)
1*
1,
#37500000
b0000000000011101 #
b0000000000011101 '
0)
0*
0,
b0000000000011101 .
b0000000000011101 /
b0000000000011101 2
#38000000
1)
1*
1,
#38500000
b0000000000011110 #
b0000000000011110 '
0)
0*
0,
b0000000000011110 .
b0000000000011110 /
b0000000000011110 2
#39000000
0!
0%
1)
1*
0+
1,
#39500000
b0000000000011111 #
b0000000000011111 '
0)
0*
0,
b0000000000011111 .
b0000000000011111 /
b0000000000011111 2
