src/components/control/decoder.vhd

-- Descrição de Hardware (VHDL) de uma porta AND de duas entradas
--
--                          _____				
--                         |     |
--      op_code (4bits) >--| DEC |--> control_signals
--                         |_____|
--
--
-- AUTOR: André Solano F. R. Maiolini
-- DATA: 21/06/2024

--| Libraries |-------------------------------------------------------

library ieee;
use ieee.std_logic_1164.all;

--| AND gate |---------------------------------------------------------

-- Definindo uma entidade para o AND gate

entity decoder is
  
  port (
    op_code       : in  std_logic_vector(3 downto 0);
    sel_ula_src   : out std_logic;
    WR_RAM        : out std_logic;
    WR_PC         : out std_logic;
    WR_ACC        : out std_logic;
    sel_acc_src_1 : out std_logic;
    sel_acc_src_0 : out std_logic;
    op_ula        : out std_logic
  );

end decoder;

--| Architecture |-----------------------------------------------------

-- Definindo a lógica do AND gate

architecture main of decoder is

  signal u, v, w, x, y : std_logic;

begin

  -- SelUlaSrc
  sel_ula_src <= (not(op_code(3)) and op_code(2)) and op_code(0);
   
  -- WR_RAM
  u <= (not(op_code(3)) and not(op_code(2))) and not(op_code(1));
  WR_RAM <= u and op_code(0);

  -- WR_PC
  WR_PC <= ((op_code(3) or op_code(2)) or op_code(1)) or op_code(0);

  -- WR_ACC
  v <= (not(op_code(3)) and op_code(2));
  w <= (op_code(1) and not(op_code(3)));
  WR_ACC <= v or w;

  -- SelAccSrc1
  sel_acc_src_1 <= not(op_code(3)) and op_code(2);

  -- SelAccSrc0
  sel_acc_src_0 <= (((not(op_code(3)) and not(op_code(2))) and op_code(1)) and op_code(0));

  -- op_ula
  x <= not(op_code(3)) and not(op_code(2));
  y <= not(op_code(1)) and not(op_code(3));
  op_ula <= x or y;

end architecture main;

---------------------------------------------------------------------

src/components/register/register_sync_16bit.vhd
-- Descrição de Hardware (VHDL) de um Registrador Síncrono 16 bits c/ CLEAR e PRESET
--
--                  __________
--      not(PR) >--|          |
--      not(CL) >--| register |-->      Q (16 bits)
--      data_in >--|  16 bits |--> not(Q) (16 bits)
--       enable >--|          |
--          CLK >--|__________|
--
--
-- AUTOR: André Solano F. R. Maiolini
-- DATA: 23/06/2024

--| Libraries |--------------------------------------------------------------------------

library ieee;
use ieee.std_logic_1164.all;

--| Register |---------------------------------------------------------------------------

entity register_sync_16bit is
    port (
        data_in   : in  std_logic_vector(15 downto 0);  -- Dados de entrada
        enable    : in  std_logic;                      -- Sinal de habilitação
        MR        : in  std_logic;                      -- Sinal de master-reset
        CLK       : in  std_logic;                      -- Sinal de clock
        data_out  : out std_logic_vector(15 downto 0)   -- Dados de saída
    );
end entity register_sync_16bit;

--| Lógica |------------------------------------------------------------------------------

architecture main of register_sync_16bit is
begin

    process (CLK, MR)
    begin
        if MR = '0' then
            data_out <= x"0000";
        elsif falling_edge(CLK) then
            if enable = '1' then
                data_out <= data_in;
            end if;
        end if;
    end process;

end architecture main;

src/components/memory/generic_rom.vhd
-- Descrição de Hardware (VHDL) de uma Read Only Memory (ROM)
--
--                    _________
--           addr >--|         |--> data_out
--       CS (LOW) >--|   ROM   |
--       OE (LOW) >--|_________|
--                
-- 
-- Requisitos
-- > Read Only Memory: somente leitura.
--
-- AUTOR: André Solano F. R. Maiolini
-- DATA: 23/06/2024

--| Libraries |-----------------------------------------------------------------------------------

library ieee;
use ieee.std_logic_1164.all;
use ieee.numeric_std.all;

--| ROM |-----------------------------------------------------------------------------------------

entity generic_rom is

    generic (
        n      : integer := 8;                                 -- Quantidade de bits de endereçamento
        word   : integer := 16                                 -- Tamanho da palavra de memória
    );

    port (
        cs       : in std_logic;                               -- Chip Selection (CS) ativo em LOW
        oe       : in std_logic;                               -- Output Enable (OE) ativo em LOW
        address  : in std_logic_vector(n-1 downto 0);          -- Barramento de endereço
        data_out : out std_logic_vector(word-1 downto 0)       -- Saída de dados
    );
    
end entity generic_rom;

--| Lógica |--------------------------------------------------------------------------------------

architecture main of generic_rom is

    type memory_type is array (0 to 2**n - 1) of std_logic_vector(word-1 downto 0);
    constant memory : memory_type := (
        0 => x"0000",
        1 => x"1000",
        2 => x"2000",
        3 => x"3000",
        4 => x"4000",
        5 => x"5000",
        6 => x"6000",
        7 => x"7000",
        others => x"0000"
    );

begin

    process (address, cs, oe)
    begin

        if cs = '0' then      -- CS ativo (nível lógico LOW)

            if oe = '0' then  -- OE ativo (nível lógico LOW)

                data_out <= memory(to_integer(unsigned(address)));

            else

                data_out <= (others => 'Z');  -- Alta impedância quando OE não está ativo

            end if;

        else

            data_out <= (others => 'Z');      -- Alta impedância quando CS não está ativo
            
        end if;

    end process;

end architecture main;

src/components/counter/generic_counter.vhd
-- Descrição de Hardware (VHDL) de um Contador Genérico de n bits
--
--                  __________
--          clk >--|          |
--                 | Contador |--> count (n bits) 
--           MR >--|__________|
--
--
-- AUTOR: André Solano F. R. Maiolini
-- DATA: 23/06/2024

--| Libraries |------------------------------------------------------------------------------

library ieee;
use ieee.std_logic_1164.all;
use ieee.numeric_std.all;

--| Contador |--------------------------------------------------------------------------------

entity generic_counter is
    generic(n : integer := 4); -- quantidade de bits do contador
    port (
        clk    : in  std_logic;
        MR     : in  std_logic;
        count  : out std_logic_vector(n - 1 downto 0)
    );
end entity generic_counter;

--| Lógica |----------------------------------------------------------------------------------

architecture main of generic_counter is

    signal count_temp : unsigned(n-1 downto 0);

begin

    contagem : process(clk, MR) 
    begin

        if MR = '0' then

            count_temp <= (others => '0');

        elsif falling_edge(clk) then

            count_temp <= count_temp + 1;

        end if;

    end process contagem;

    count <= std_logic_vector(count_temp);

end architecture main;

src/components/timer/generic_timer.vhd
-- Descrição de Hardware (VHDL) de um Timer de Freq. Genérica (MHz)
--
--             _________
--            |         |
--      en >--|  Timer  |--> clk
--            |_________|
--
--
-- AUTOR: André Solano F. R. Maiolini
-- DATA: 23/06/2024

--| Libraries |------------------------------------------------------------------------------

library ieee;
use ieee.std_logic_1164.all;
use ieee.numeric_std.all;

--| Timer |----------------------------------------------------------------------------------

entity generic_timer is

    generic(
        clk_freq : integer := 4
    );

    port(
        clk : out std_logic;
        enable : in std_logic
    );

end entity generic_timer;

--| Lógica |----------------------------------------------------------------------------------

architecture main of generic_timer is
begin

    clock_generator : process
    begin
        
        clk <= '0';
        wait for (1000 ns / clk_freq);
        
        while enable = '1' loop
            clk <= not clk;
            wait for (1000 ns / clk_freq);
        end loop;

        wait;

    end process;

end architecture main;

src/cpu.vhd
--| Libraries |----------------------------------------------------------------------------------------------------
library ieee;
use ieee.std_logic_1164.all;
use ieee.numeric_std.all;

--| CPU |----------------------------------------------------------------------------------------------------------

entity cpu is

    -- Define genericamente os valores que serão fornecidos pelo arquivo de testes:

    generic(
        n        : integer := 16;                              -- Tamanho em bits do PC
        f        : integer := 2000;                            -- MHz (freq. clock)
        addr_rom : integer := 16;                              -- Bits de endereçamento ROM (instruções)
        i_word   : integer := 16                               -- Tamanho da palavra de instrução
    );

    -- Define as portas da CPU - entradas, saídas e tipos básicos:

    port(
        enable_clk  : in  std_logic;                           -- Habilita pulsos de clock
        MR          : in  std_logic;                           -- Master-Reset (ativo em LOW)
        pc_count    : out std_logic_vector(n-1 downto 0);      -- Program Counter (PC)
        d_out       : out std_logic;                           -- Sinal de controle
        op_out      : out std_logic_vector(3 downto 0)         -- Código de operação
    );

end entity cpu;

--| Lógica |--------------------------------------------------------------------------------------------------------

architecture main of cpu is

    -- Definindo sinais internos à CPU:

    signal internal_clk : std_logic;                            -- Clock interno da CPU (recebe o clock do TIMER)
    signal inst_data    : std_logic_vector(i_word-1 downto 0);  -- Define a instrução que será carregada no IR
    signal instruction  : std_logic_vector(i_word-1 downto 0);  -- Instrução lida da saída do IR
    signal op_code      : std_logic_vector(3 downto 0);         -- Código de operação
    signal operand      : std_logic_vector(11 downto 0);        -- Operando 12 bits
    signal operand_ex   : std_logic_vector(15 downto 0);        -- Operando extendido (16 bits)

    -- Definindo sinais de controle:

    signal SelUlaSrc    : std_logic;                            -- Sinal de seleção da fonte para a ALU
    signal OP_ULA       : std_logic;                            -- Sinal de seleção de operação da ALU
    signal WR_RAM       : std_logic;                            -- Sinal de escrita na memória de dados (RAM)
    signal WR_PC        : std_logic;                            -- Sinal de incremento do PC (modificar)
    signal WR_IR        : std_logic := '1';                     -- Sinal de controle WR_IR
    signal WR_ACC       : std_logic;                            -- Sinal de escrita no acumulador (ACC)
    signal SelAccSrc1   : std_logic;                            -- Seleciona dados para o ACC (MSB)
    signal SelACCSrc0   : std_logic;                            -- Seleciona dados para o ACC (LSB)

    -- Definindo os componentes internos da CPU:

        -- Temporizador genérico:

        component generic_timer is
            generic(
                clk_freq : integer := f      -- Define a frequência do temporizador
            );
            port(
                clk : out std_logic := '0';
                enable : in std_logic
            );
        end component generic_timer;

        -- Contador genérico:

        component generic_counter is
            generic(
                n : integer := n                          -- Define a largura de bits do contador
            );
            port (
                clk    : in  std_logic;
                MR     : in  std_logic;
                count  : out std_logic_vector(n - 1 downto 0)
            );
        end component generic_counter;

        -- Read Only Memory:

        component generic_rom is
            generic (
                n      : integer := addr_rom;   -- Quantidade de bits de endereçamento
                word   : integer := i_word      -- Tamanho da palavra de memória
            );
            port (
                cs       : in std_logic;                               -- Chip Selection (CS) ativo em LOW
                oe       : in std_logic;                               -- Output Enable (OE) ativo em LOW
                address  : in std_logic_vector(n-1 downto 0);          -- Barramento de endereço
                data_out : out std_logic_vector(word-1 downto 0)       -- Saída de dados
            );
        end component generic_rom;

        -- Registrador de 16 bits:

        component register_sync_16bit is
            port (
                data_in   : in  std_logic_vector(15 downto 0);         -- Dados de entrada
                enable    : in  std_logic;                             -- Sinal de habilitação
                MR        : in  std_logic;                             -- Sinal de master-reset
                CLK       : in  std_logic;                             -- Sinal de clock
                data_out  : out std_logic_vector(15 downto 0)          -- Dados de saída
            );
        end component register_sync_16bit;

        -- Decodificador de instruções

        component decoder is
            port (
                op_code       : in  std_logic_vector(3 downto 0);      -- Entrada do código de operação
                sel_ula_src   : out std_logic;                         -- Restante dos sinais de controle
                WR_RAM        : out std_logic;
                WR_PC         : out std_logic;
                WR_ACC        : out std_logic;
                sel_acc_src_1 : out std_logic;
                sel_acc_src_0 : out std_logic;
                op_ula        : out std_logic
            );
        end component decoder;

begin

    -- Instância o relógio interno da CPU: TIMER

    TIMER: generic_timer 
        port map(
            internal_clk,                    -- Recebe, a partir do TIMER o internal_clock
            enable_clk                       -- Sinal para habilitar o TIMER interno da CPU
        );

    -- Instância o circuito Program Counter: PC_counter

    PC_counter: generic_counter
        port map(
            internal_clk,                    -- Atribui o clock interno da CPU para o contador
            MR,                              -- Sinal de Master-Reset do PC_counter
            pc_count                         -- Direciona o valor do PC para pc_count
        );

    -- Instância a memória de programa: ROM

    ROM: generic_rom
        port map(
            '0',                             -- Seleciona a memória ROM (Chip Select) - ativo em LOW
            '0',                             -- Habilita a leitura da memória de programa
            pc_count,                        -- Endereça a memória a partir do PC
            inst_data                        -- Obtém instrução a partir do endereço
        );

    -- Instância de um registrador: IR (Instruction Register)

    IR: register_sync_16bit
        port map(
            inst_data,                       -- Recebe instrução a partir do sinal da memória de programa
            WR_IR,                           -- Habilita a escrita no Instruction Register (IR)
            MR,                              -- Master Reset ativo em LOW para o registrador
            internal_clk,                    -- Sincroniza o registrador com o clock interno da CPU
            instruction                      -- Saída do dado gravado no IR
        );

    -- Lendo o op_code e operand:

    op_code <= instruction(15 downto 12);
    operand <= instruction(11 downto 0);

    -- Extensão de sinal do operando:

    operand_ex <= x"0" & operand;
    op_out <= op_code; 

    -- Instanciando o decodificador de instruções:

    DECR: decoder port map(
        op_code, SelUlaSrc, WR_RAM, WR_PC, WR_ACC, SelAccSrc1, SelAccSrc0, OP_ULA
    );

    d_out <= SelAccSrc0;

end architecture main;

--------------------------------------------------------------------------------------------------------------------

test/testbench/cpu_tb.vhd
-- Arquivo de testes (testbench) para a CPU (BIP I)

--| Libraries |----------------------------------------------------------------------------------------------------------

library ieee;
use ieee.std_logic_1164.all;

--| Entidade |-----------------------------------------------------------------------------------------------------------

entity cpu_tb is
end entity cpu_tb;

--| Lógica - Testbench |-------------------------------------------------------------------------------------------------

architecture teste of cpu_tb is
  
  -- Definições básicas do processador:

  constant n        : integer := 16;                        -- Tamanho do Program Counter (PC) da CPU em bits
  constant f        : integer := 2000;                      -- Frequência de operação do Timer Interno (MHz)
  constant i_word   : integer := 16;                        -- Palavra de instrução em bits
  constant addr_rom : integer := 16;                        -- Bits de endereçamento da ROM
  
  -- Sinais sendo rastreados:

  signal enable_clk : std_logic := '1';                       -- Enable (ativo em HIGH)
  signal MR         : std_logic;                              -- Master-Reset (ativo em LOW)
  signal pc_count   : std_logic_vector(n-1 downto 0);         -- Program Count
  signal d_out      : std_logic;                              -- Sinal de controle
  signal op_out     : std_logic_vector(3 downto 0);           -- Código de operação

  -- Declaração do componente CPU:

  component cpu is

    generic(
        n        : integer := n;
        f        : integer := f;
        addr_rom : integer := addr_rom;
        i_word   : integer := i_word
    );

    port(
        enable_clk  : in  std_logic;                           -- Habilita pulsos de clock
        MR          : in  std_logic;                           -- Master-Reset (ativo em LOW)
        pc_count    : out std_logic_vector(n-1 downto 0);      -- Program Count
        d_out       : out std_logic;                           -- Sinal de controle
        op_out      : out std_logic_vector(3 downto 0)         -- Código de operação
    );

  end component cpu;

begin

    -- Instanciando o BIP (do tipo cpu) e declarando as portas:

    BIP: cpu port map (enable_clk, MR, pc_count, d_out, op_out);

    -- Testando o Program Counter (PC) do BIP:

    test: process
    begin

        MR <= '0';
        wait for 1 ns;
        MR <= '1';
        wait for 7 ns;
        MR <= '0';
        wait for 1 ns;
        MR <= '1';
        wait for 30 ns;
        enable_clk <= '0';

        wait;

    end process test;

end architecture teste;

test/waveform/cpu_tb.vcd
$date
  Sun Jun 23 23:34:58 2024
$end
$version
  GHDL v0
$end
$timescale
  1 fs
$end
$scope module standard $end
$upscope $end
$scope module textio $end
$upscope $end
$scope module std_logic_1164 $end
$upscope $end
$scope module numeric_std $end
$upscope $end
$scope module cpu_tb $end
$var reg 1 ! enable_clk $end
$var reg 1 " mr $end
$var reg 16 # pc_count[15:0] $end
$var reg 1 $ d_out $end
$var reg 4 % op_out[3:0] $end
$scope module bip $end
$var reg 1 & enable_clk $end
$var reg 1 ' mr $end
$var reg 16 ( pc_count[15:0] $end
$var reg 1 ) d_out $end
$var reg 4 * op_out[3:0] $end
$var reg 1 + internal_clk $end
$var reg 16 , inst_data[15:0] $end
$var reg 16 - instruction[15:0] $end
$var reg 4 . op_code[3:0] $end
$var reg 12 / operand[11:0] $end
$var reg 16 0 operand_ex[15:0] $end
$var reg 1 1 selulasrc $end
$var reg 1 2 op_ula $end
$var reg 1 3 wr_ram $end
$var reg 1 4 wr_pc $end
$var reg 1 5 wr_ir $end
$var reg 1 6 wr_acc $end
$var reg 1 7 selaccsrc1 $end
$var reg 1 8 selaccsrc0 $end
$scope module timer $end
$var reg 1 9 clk $end
$var reg 1 : enable $end
$upscope $end
$scope module pc_counter $end
$var reg 1 ; clk $end
$var reg 1 < mr $end
$var reg 16 = count[15:0] $end
$var reg 16 > count_temp[15:0] $end
$upscope $end
$scope module rom $end
$var reg 1 ? cs $end
$var reg 1 @ oe $end
$var reg 16 A address[15:0] $end
$var reg 16 B data_out[15:0] $end
$upscope $end
$scope module ir $end
$var reg 16 C data_in[15:0] $end
$var reg 1 D enable $end
$var reg 1 E mr $end
$var reg 1 F clk $end
$var reg 16 G data_out[15:0] $end
$upscope $end
$scope module decr $end
$var reg 4 H op_code[3:0] $end
$var reg 1 I sel_ula_src $end
$var reg 1 J wr_ram $end
$var reg 1 K wr_pc $end
$var reg 1 L wr_acc $end
$var reg 1 M sel_acc_src_1 $end
$var reg 1 N sel_acc_src_0 $end
$var reg 1 O op_ula $end
$var reg 1 P u $end
$var reg 1 Q v $end
$var reg 1 R w $end
$var reg 1 S x $end
$var reg 1 T y $end
$upscope $end
$upscope $end
$upscope $end
$enddefinitions $end
#0
1!
0"
b0000000000000000 #
0$
b0000 %
1&
0'
b0000000000000000 (
0)
b0000 *
1+
b0000000000000000 ,
b0000000000000000 -
b0000 .
b000000000000 /
b0000000000000000 0
01
12
03
04
15
06
07
08
19
1:
1;
0<
b0000000000000000 =
b0000000000000000 >
0?
0@
b0000000000000000 A
b0000000000000000 B
b0000000000000000 C
1D
0E
1F
b0000000000000000 G
b0000 H
0I
0J
0K
0L
0M
0N
1O
1P
0Q
0R
1S
1T
#500000
0+
09
0;
0F
#1000000
1"
1'
1+
19
1;
1<
1E
1F
#1500000
b0000000000000001 #
b0000000000000001 (
0+
b0001000000000000 ,
09
0;
b0000000000000001 =
b0000000000000001 >
b0000000000000001 A
b0001000000000000 B
b0001000000000000 C
0F
#2000000
1+
19
1;
1F
#2500000
b0000000000000010 #
b0001 %
b0000000000000010 (
b0001 *
0+
b0010000000000000 ,
b0001000000000000 -
b0001 .
13
14
09
0;
b0000000000000010 =
b0000000000000010 >
b0000000000000010 A
b0010000000000000 B
b0010000000000000 C
0F
b0001000000000000 G
b0001 H
1J
1K
#3000000
1+
19
1;
1F
#3500000
b0000000000000011 #
b0010 %
b0000000000000011 (
b0010 *
0+
b0011000000000000 ,
b0010000000000000 -
b0010 .
03
16
09
0;
b0000000000000011 =
b0000000000000011 >
b0000000000000011 A
b0011000000000000 B
b0011000000000000 C
0F
b0010000000000000 G
b0010 H
0J
1L
0P
1R
0T
#4000000
1+
19
1;
1F
#4500000
b0000000000000100 #
1$
b0011 %
b0000000000000100 (
1)
b0011 *
0+
b0100000000000000 ,
b0011000000000000 -
b0011 .
18
09
0;
b0000000000000100 =
b0000000000000100 >
b0000000000000100 A
b0100000000000000 B
b0100000000000000 C
0F
b0011000000000000 G
b0011 H
1N
#5000000
1+
19
1;
1F
#5500000
b0000000000000101 #
0$
b0100 %
b0000000000000101 (
0)
b0100 *
0+
b0101000000000000 ,
b0100000000000000 -
b0100 .
17
08
09
0;
b0000000000000101 =
b0000000000000101 >
b0000000000000101 A
b0101000000000000 B
b0101000000000000 C
0F
b0100000000000000 G
b0100 H
1M
0N
1Q
0R
0S
1T
#6000000
1+
19
1;
1F
#6500000
b0000000000000110 #
b0101 %
b0000000000000110 (
b0101 *
0+
b0110000000000000 ,
b0101000000000000 -
b0101 .
11
09
0;
b0000000000000110 =
b0000000000000110 >
b0000000000000110 A
b0110000000000000 B
b0110000000000000 C
0F
b0101000000000000 G
b0101 H
1I
#7000000
1+
19
1;
1F
#7500000
b0000000000000111 #
b0110 %
b0000000000000111 (
b0110 *
0+
b0111000000000000 ,
b0110000000000000 -
b0110 .
01
02
09
0;
b0000000000000111 =
b0000000000000111 >
b0000000000000111 A
b0111000000000000 B
b0111000000000000 C
0F
b0110000000000000 G
b0110 H
0I
0O
1R
0T
#8000000
0"
b0000000000000000 #
b0000 %
0'
b0000000000000000 (
b0000 *
1+
b0000000000000000 ,
b0000000000000000 -
b0000 .
12
04
06
07
19
1;
0<
b0000000000000000 =
b0000000000000000 >
b0000000000000000 A
b0000000000000000 B
b0000000000000000 C
0E
1F
b0000000000000000 G
b0000 H
0K
0L
0M
1O
1P
0Q
0R
1S
1T
#8500000
0+
09
0;
0F
#9000000
1"
1'
1+
19
1;
1<
1E
1F
#9500000
b0000000000000001 #
b0000000000000001 (
0+
b0001000000000000 ,
09
0;
b0000000000000001 =
b0000000000000001 >
b0000000000000001 A
b0001000000000000 B
b0001000000000000 C
0F
#10000000
1+
19
1;
1F
#10500000
b0000000000000010 #
b0001 %
b0000000000000010 (
b0001 *
0+
b0010000000000000 ,
b0001000000000000 -
b0001 .
13
14
09
0;
b0000000000000010 =
b0000000000000010 >
b0000000000000010 A
b0010000000000000 B
b0010000000000000 C
0F
b0001000000000000 G
b0001 H
1J
1K
#11000000
1+
19
1;
1F
#11500000
b0000000000000011 #
b0010 %
b0000000000000011 (
b0010 *
0+
b0011000000000000 ,
b0010000000000000 -
b0010 .
03
16
09
0;
b0000000000000011 =
b0000000000000011 >
b0000000000000011 A
b0011000000000000 B
b0011000000000000 C
0F
b0010000000000000 G
b0010 H
0J
1L
0P
1R
0T
#12000000
1+
19
1;
1F
#12500000
b0000000000000100 #
1$
b0011 %
b0000000000000100 (
1)
b0011 *
0+
b0100000000000000 ,
b0011000000000000 -
b0011 .
18
09
0;
b0000000000000100 =
b0000000000000100 >
b0000000000000100 A
b0100000000000000 B
b0100000000000000 C
0F
b0011000000000000 G
b0011 H
1N
#13000000
1+
19
1;
1F
#13500000
b0000000000000101 #
0$
b0100 %
b0000000000000101 (
0)
b0100 *
0+
b0101000000000000 ,
b0100000000000000 -
b0100 .
17
08
09
0;
b0000000000000101 =
b0000000000000101 >
b0000000000000101 A
b0101000000000000 B
b0101000000000000 C
0F
b0100000000000000 G
b0100 H
1M
0N
1Q
0R
0S
1T
#14000000
1+
19
1;
1F
#14500000
b0000000000000110 #
b0101 %
b0000000000000110 (
b0101 *
0+
b0110000000000000 ,
b0101000000000000 -
b0101 .
11
09
0;
b0000000000000110 =
b0000000000000110 >
b0000000000000110 A
b0110000000000000 B
b0110000000000000 C
0F
b0101000000000000 G
b0101 H
1I
#15000000
1+
19
1;
1F
#15500000
b0000000000000111 #
b0110 %
b0000000000000111 (
b0110 *
0+
b0111000000000000 ,
b0110000000000000 -
b0110 .
01
02
09
0;
b0000000000000111 =
b0000000000000111 >
b0000000000000111 A
b0111000000000000 B
b0111000000000000 C
0F
b0110000000000000 G
b0110 H
0I
0O
1R
0T
#16000000
1+
19
1;
1F
#16500000
b0000000000001000 #
b0111 %
b0000000000001000 (
b0111 *
0+
b0000000000000000 ,
b0111000000000000 -
b0111 .
11
09
0;
b0000000000001000 =
b0000000000001000 >
b0000000000001000 A
b0000000000000000 B
b0000000000000000 C
0F
b0111000000000000 G
b0111 H
1I
#17000000
1+
19
1;
1F
#17500000
b0000000000001001 #
b0000 %
b0000000000001001 (
b0000 *
0+
b0000000000000000 -
b0000 .
01
12
04
06
07
09
0;
b0000000000001001 =
b0000000000001001 >
b0000000000001001 A
0F
b0000000000000000 G
b0000 H
0I
0K
0L
0M
1O
1P
0Q
0R
1S
1T
#18000000
1+
19
1;
1F
#18500000
b0000000000001010 #
b0000000000001010 (
0+
09
0;
b0000000000001010 =
b0000000000001010 >
b0000000000001010 A
0F
#19000000
1+
19
1;
1F
#19500000
b0000000000001011 #
b0000000000001011 (
0+
09
0;
b0000000000001011 =
b0000000000001011 >
b0000000000001011 A
0F
#20000000
1+
19
1;
1F
#20500000
b0000000000001100 #
b0000000000001100 (
0+
09
0;
b0000000000001100 =
b0000000000001100 >
b0000000000001100 A
0F
#21000000
1+
19
1;
1F
#21500000
b0000000000001101 #
b0000000000001101 (
0+
09
0;
b0000000000001101 =
b0000000000001101 >
b0000000000001101 A
0F
#22000000
1+
19
1;
1F
#22500000
b0000000000001110 #
b0000000000001110 (
0+
09
0;
b0000000000001110 =
b0000000000001110 >
b0000000000001110 A
0F
#23000000
1+
19
1;
1F
#23500000
b0000000000001111 #
b0000000000001111 (
0+
09
0;
b0000000000001111 =
b0000000000001111 >
b0000000000001111 A
0F
#24000000
1+
19
1;
1F
#24500000
b0000000000010000 #
b0000000000010000 (
0+
09
0;
b0000000000010000 =
b0000000000010000 >
b0000000000010000 A
0F
#25000000
1+
19
1;
1F
#25500000
b0000000000010001 #
b0000000000010001 (
0+
09
0;
b0000000000010001 =
b0000000000010001 >
b0000000000010001 A
0F
#26000000
1+
19
1;
1F
#26500000
b0000000000010010 #
b0000000000010010 (
0+
09
0;
b0000000000010010 =
b0000000000010010 >
b0000000000010010 A
0F
#27000000
1+
19
1;
1F
#27500000
b0000000000010011 #
b0000000000010011 (
0+
09
0;
b0000000000010011 =
b0000000000010011 >
b0000000000010011 A
0F
#28000000
1+
19
1;
1F
#28500000
b0000000000010100 #
b0000000000010100 (
0+
09
0;
b0000000000010100 =
b0000000000010100 >
b0000000000010100 A
0F
#29000000
1+
19
1;
1F
#29500000
b0000000000010101 #
b0000000000010101 (
0+
09
0;
b0000000000010101 =
b0000000000010101 >
b0000000000010101 A
0F
#30000000
1+
19
1;
1F
#30500000
b0000000000010110 #
b0000000000010110 (
0+
09
0;
b0000000000010110 =
b0000000000010110 >
b0000000000010110 A
0F
#31000000
1+
19
1;
1F
#31500000
b0000000000010111 #
b0000000000010111 (
0+
09
0;
b0000000000010111 =
b0000000000010111 >
b0000000000010111 A
0F
#32000000
1+
19
1;
1F
#32500000
b0000000000011000 #
b0000000000011000 (
0+
09
0;
b0000000000011000 =
b0000000000011000 >
b0000000000011000 A
0F
#33000000
1+
19
1;
1F
#33500000
b0000000000011001 #
b0000000000011001 (
0+
09
0;
b0000000000011001 =
b0000000000011001 >
b0000000000011001 A
0F
#34000000
1+
19
1;
1F
#34500000
b0000000000011010 #
b0000000000011010 (
0+
09
0;
b0000000000011010 =
b0000000000011010 >
b0000000000011010 A
0F
#35000000
1+
19
1;
1F
#35500000
b0000000000011011 #
b0000000000011011 (
0+
09
0;
b0000000000011011 =
b0000000000011011 >
b0000000000011011 A
0F
#36000000
1+
19
1;
1F
#36500000
b0000000000011100 #
b0000000000011100 (
0+
09
0;
b0000000000011100 =
b0000000000011100 >
b0000000000011100 A
0F
#37000000
1+
19
1;
1F
#37500000
b0000000000011101 #
b0000000000011101 (
0+
09
0;
b0000000000011101 =
b0000000000011101 >
b0000000000011101 A
0F
#38000000
1+
19
1;
1F
#38500000
b0000000000011110 #
b0000000000011110 (
0+
09
0;
b0000000000011110 =
b0000000000011110 >
b0000000000011110 A
0F
#39000000
0!
0&
1+
19
0:
1;
1F
#39500000
b0000000000011111 #
b0000000000011111 (
0+
09
0;
b0000000000011111 =
b0000000000011111 >
b0000000000011111 A
0F
