src/components/register/register_sync_16bit.vhd
-- Descrição de Hardware (VHDL) de um Registrador Síncrono 16 bits c/ CLEAR e PRESET
--
--                  __________
--      not(PR) >--|          |
--      not(CL) >--| register |-->      Q (16 bits)
--      data_in >--|  16 bits |--> not(Q) (16 bits)
--       enable >--|          |
--          CLK >--|__________|
--
--
-- AUTOR: André Solano F. R. Maiolini
-- DATA: 23/06/2024

--| Libraries |--------------------------------------------------------------------------

library ieee;
use ieee.std_logic_1164.all;

--| Register |---------------------------------------------------------------------------

entity register_sync_16bit is
    port (
        data_in   : in  std_logic_vector(15 downto 0);  -- Dados de entrada
        enable    : in  std_logic;                      -- Sinal de habilitação
        MR        : in  std_logic;                      -- Sinal de master-reset
        CLK       : in  std_logic;                      -- Sinal de clock
        data_out  : out std_logic_vector(15 downto 0)   -- Dados de saída
    );
end entity register_sync_16bit;

--| Lógica |------------------------------------------------------------------------------

architecture main of register_sync_16bit is
begin

    process (CLK, MR)
    begin
        if MR = '0' then
            data_out <= x"0000";
        elsif falling_edge(CLK) then
            if enable = '1' then
                data_out <= data_in;
            end if;
        end if;
    end process;

end architecture main;

src/components/memory/generic_rom.vhd

-- =======================================================================================================
--
--  Descrição de Hardware (VHDL) de uma Read Only Memory (ROM) - "Memória de Programa"
--
--  ->> AUTOR: André Solano F. R. Maiolini
--  ->> DATA: 23/06/2024
--
--   ██████╗  ██████╗ ███╗   ███╗
--   ██╔══██╗██╔═══██╗████╗ ████║
--   ██████╔╝██║   ██║██╔████╔██║
--   ██╔══██╗██║   ██║██║╚██╔╝██║
--   ██║  ██║╚██████╔╝██║ ╚═╝ ██║
--   ╚═╝  ╚═╝ ╚═════╝ ╚═╝     ╚═╝
--
--  ->> Diagrama de bloco (entradas e saídas) ============================================================
--
--                    _________
--           addr >--|         |--> data_out
--       CS (LOW) >--|   ROM   |
--       OE (LOW) >--|_________|
--                
-- =======================================================================================================

--| Libraries |-------------------------------------------------------------------------------------------

library ieee;
use ieee.std_logic_1164.all;
use ieee.numeric_std.all;

--| ROM |-------------------------------------------------------------------------------------------------

entity generic_rom is

    generic (
        n      : integer := 8;                                 -- Quantidade de bits de endereçamento
        word   : integer := 16                                 -- Tamanho da palavra de memória
    );

    port (
        cs       : in std_logic;                               -- Chip Selection (CS) ativo em LOW
        oe       : in std_logic;                               -- Output Enable (OE) ativo em LOW
        address  : in std_logic_vector(n-1 downto 0);          -- Barramento de endereço
        data_out : out std_logic_vector(word-1 downto 0)       -- Saída de dados
    );
    
end entity generic_rom;

--| Lógica |----------------------------------------------------------------------------------------------

architecture main of generic_rom is

    -- (PROGRAMA DE TESTE) ------------------------------------------------------------------------------

    -- Nesta seção estão os programas de teste para as funcionalidades e operações do BIP-1.

    type memory_type is array (0 to 2**n - 1) of std_logic_vector(word-1 downto 0);

    -- Gravação do código a ser executado pela CPU:

    -- Teste: "Cálculo de 5! (fatorial de 5)"

    constant memory : memory_type := (                                                                                                                                                            
        0  => x"3001",   -- 0 : 3001                                                                                                                                                              
        1  => x"1000",   -- 1 : 1000
        2  => x"3005",   -- 2 : 3005
        3  => x"1001",   -- 3 : 1001
        4  => x"3000",   -- 4 : 3000
        5  => x"1006",   -- 5 : 1006
        6  => x"2001",   -- 6 : 2001
        7  => x"A006",   -- 7 : A006
        8  => x"B00A",   -- 8 : B00A
        9  => x"8022",   -- 9 : 8022
        10 => x"2001",   -- A : 2001
        11 => x"1002",   -- B : 1002
        12 => x"2000",   -- C : 2000
        13 => x"1003",   -- D : 1003
        14 => x"8015",   -- E : 8015
        15 => x"2004",   -- F : 2004
        16 => x"1000",   -- 10 : 1000
        17 => x"2001",   -- 11 : 2001
        18 => x"7001",   -- 12 : 7001
        19 => x"1001",   -- 13 : 1001
        20 => x"8006",   -- 14 : 8006
        21 => x"3000",   -- 15 : 3000
        22 => x"1004",   -- 16 : 1004
        23 => x"3000",   -- 17 : 3000
        24 => x"1005",   -- 18 : 1005
        25 => x"2004",   -- 19 : 2004
        26 => x"4003",   -- 1A : 4003
        27 => x"1004",   -- 1B : 1004
        28 => x"2002",   -- 1C : 2002
        29 => x"7001",   -- 1D : 7001
        30 => x"1002",   -- 1E : 1002
        31 => x"A005",   -- 1F : A005
        32 => x"B019",   -- 20 : B019
        33 => x"800F",   -- 21 : 800F
        34 => x"2000",   -- 22 : 2000
        35 => x"0000",   -- 23 : 0000
        others => x"0000"
    );

begin

    process (address, cs, oe)
    begin

        if cs = '0' then      -- CS ativo (nível lógico LOW)

            if oe = '0' then  -- OE ativo (nível lógico LOW)

                data_out <= memory(to_integer(unsigned(address)));

            else

                data_out <= (others => 'Z');  -- Alta impedância quando OE não está ativo

            end if;

        else

            data_out <= (others => 'Z');      -- Alta impedância quando CS não está ativo
            
        end if;

    end process;

end architecture main;

-- =======================================================================================================

src/components/counter/generic_counter.vhd
-- Descrição de Hardware (VHDL) de um Contador Genérico de n bits
--
--                  __________
--          clk >--|          |
--                 | Contador |--> count (n bits) 
--           MR >--|__________|
--
--
-- AUTOR: André Solano F. R. Maiolini
-- DATA: 23/06/2024

--| Libraries |------------------------------------------------------------------------------

library ieee;
use ieee.std_logic_1164.all;
use ieee.numeric_std.all;

--| Contador |--------------------------------------------------------------------------------

entity generic_counter is
    generic(n : integer := 4); -- quantidade de bits do contador
    port (
        clk    : in  std_logic;
        MR     : in  std_logic;
        count  : out std_logic_vector(n - 1 downto 0)
    );
end entity generic_counter;

--| Lógica |----------------------------------------------------------------------------------

architecture main of generic_counter is

    signal count_temp : unsigned(n-1 downto 0);

begin

    contagem : process(clk, MR) 
    begin

        if MR = '0' then

            count_temp <= (others => '0');

        elsif falling_edge(clk) then

            count_temp <= count_temp + 1;

        end if;

    end process contagem;

    count <= std_logic_vector(count_temp);

end architecture main;

src/components/timer/generic_timer.vhd
-- Descrição de Hardware (VHDL) de um Timer de Freq. Genérica (MHz)
--
--             _________
--            |         |
--      en >--|  Timer  |--> clk
--            |_________|
--
--
-- AUTOR: André Solano F. R. Maiolini
-- DATA: 23/06/2024

--| Libraries |------------------------------------------------------------------------------

library ieee;
use ieee.std_logic_1164.all;
use ieee.numeric_std.all;

--| Timer |----------------------------------------------------------------------------------

entity generic_timer is

    generic(
        clk_freq : integer := 4
    );

    port(
        clk : out std_logic;
        enable : in std_logic
    );

end entity generic_timer;

--| Lógica |----------------------------------------------------------------------------------

architecture main of generic_timer is
begin

    clock_generator : process
    begin
        
        clk <= '0';
        wait for (1000 ns / clk_freq);
        
        while enable = '1' loop
            clk <= not clk;
            wait for (1000 ns / clk_freq);
        end loop;

        wait;

    end process;

end architecture main;

src/cpu.vhd
--| Libraries |----------------------------------------------------------------------------------------------------
library ieee;
use ieee.std_logic_1164.all;
use ieee.numeric_std.all;

--| CPU |----------------------------------------------------------------------------------------------------------

entity cpu is

    -- Define genericamente os valores que serão fornecidos pelo arquivo de testes:

    generic(
        n        : integer := 16;                              -- Tamanho em bits do PC
        f        : integer := 2000;                            -- MHz (freq. clock)
        addr_rom : integer := 16;                              -- Bits de endereçamento ROM (instruções)
        i_word   : integer := 16                               -- Tamanho da palavra de instrução
    );

    -- Define as portas da CPU - entradas, saídas e tipos básicos:

    port(
        enable_clk  : in  std_logic;                           -- Habilita pulsos de clock
        MR          : in  std_logic;                           -- Master-Reset (ativo em LOW)
        pc_count    : out std_logic_vector(n-1 downto 0);      -- Program Counter (PC)
        inst_out    : out std_logic_vector(i_word-1 downto 0)  -- Leitura do IR
    );

end entity cpu;

--| Lógica |--------------------------------------------------------------------------------------------------------

architecture main of cpu is

    -- Definindo sinais internos à CPU:

    signal internal_clk : std_logic;                            -- Clock interno da CPU (recebe o clock do TIMER)
    signal instruction  : std_logic_vector(i_word-1 downto 0);  -- Define a instrução que será carregada no IR
    signal WR_IR        : std_logic := '1';                     -- Sinal de controle WR_IR

    -- Definindo os componentes internos da CPU:

        -- Temporizador genérico:

        component generic_timer is
            generic(
                clk_freq : integer := f      -- Define a frequência do temporizador
            );
            port(
                clk : out std_logic := '0';
                enable : in std_logic
            );
        end component generic_timer;

        -- Contador genérico:

        component generic_counter is
            generic(
                n : integer := n                          -- Define a largura de bits do contador
            );
            port (
                clk    : in  std_logic;
                MR     : in  std_logic;
                count  : out std_logic_vector(n - 1 downto 0)
            );
        end component generic_counter;

        -- Read Only Memory:

        component generic_rom is
            generic (
                n      : integer := addr_rom;   -- Quantidade de bits de endereçamento
                word   : integer := i_word      -- Tamanho da palavra de memória
            );
            port (
                cs       : in std_logic;                               -- Chip Selection (CS) ativo em LOW
                oe       : in std_logic;                               -- Output Enable (OE) ativo em LOW
                address  : in std_logic_vector(n-1 downto 0);          -- Barramento de endereço
                data_out : out std_logic_vector(word-1 downto 0)       -- Saída de dados
            );
        end component generic_rom;

        -- Registrador de 16 bits:

        component register_sync_16bit is
            port (
                data_in   : in  std_logic_vector(15 downto 0);  -- Dados de entrada
                enable    : in  std_logic;                      -- Sinal de habilitação
                MR        : in  std_logic;                      -- Sinal de master-reset
                CLK       : in  std_logic;                      -- Sinal de clock
                data_out  : out std_logic_vector(15 downto 0)   -- Dados de saída
            );
        end component register_sync_16bit;

begin

    -- Instância o relógio interno da CPU: TIMER

    TIMER: generic_timer 
        port map(
            internal_clk,                    -- Recebe, a partir do TIMER o internal_clock
            enable_clk                       -- Sinal para habilitar o TIMER interno da CPU
        );

    -- Instância o circuito Program Counter: PC_counter

    PC_counter: generic_counter
        port map(
            internal_clk,                    -- Atribui o clock interno da CPU para o contador
            MR,                              -- Sinal de Master-Reset do PC_counter
            pc_count                         -- Direciona o valor do PC para pc_count
        );

    -- Instância a memória de programa: ROM

    ROM: generic_rom
        port map(
            '0',                             -- Seleciona a memória ROM (Chip Select) - ativo em LOW
            '0',                             -- Habilita a leitura da memória de programa
            pc_count,                        -- Endereça a memória a partir do PC
            instruction                      -- Obtém instrução a partir do endereço
        );

    -- Instância de um registrador: IR (Instruction Register)

    IR: register_sync_16bit
        port map(
            instruction,                     -- Recebe instrução a partir do sinal da memória de programa
            WR_IR,                           -- Habilita a escrita no Instruction Register (IR)
            MR,                              -- Master Reset ativo em LOW para o registrador
            internal_clk,                    -- Sincroniza o registrador com o clock interno da CPU
            inst_out                         -- Saída do dado gravado no IR
        );

end architecture main;

--------------------------------------------------------------------------------------------------------------------

test/testbench/cpu_tb.vhd
-- Arquivo de testes (testbench) para a CPU (BIP I)

--| Libraries |----------------------------------------------------------------------------------------------------------

library ieee;
use ieee.std_logic_1164.all;

--| Entidade |-----------------------------------------------------------------------------------------------------------

entity cpu_tb is
end entity cpu_tb;

--| Lógica - Testbench |-------------------------------------------------------------------------------------------------

architecture teste of cpu_tb is
  
  -- Definições básicas do processador:

  constant n        : integer := 16;                        -- Tamanho do Program Counter (PC) da CPU em bits
  constant f        : integer := 2000;                      -- Frequência de operação do Timer Interno (MHz)
  constant i_word   : integer := 16;                        -- Palavra de instrução em bits
  constant addr_rom : integer := 16;                        -- Bits de endereçamento da ROM
  
  -- Sinais sendo rastreados:

  signal enable_clk : std_logic := '1';                       -- Enable (ativo em HIGH)
  signal MR         : std_logic;                              -- Master-Reset (ativo em LOW)
  signal pc_count   : std_logic_vector(n-1 downto 0);         -- Program Count
  signal inst_out   : std_logic_vector(i_word-1 downto 0);    -- Instrução lida do IR

  -- Declaração do componente CPU:

  component cpu is

    generic(
        n        : integer := n;
        f        : integer := f;
        addr_rom : integer := addr_rom;
        i_word   : integer := i_word
    );

    port(
        enable_clk  : in  std_logic;                          -- Habilita pulsos de clock
        MR          : in  std_logic;                          -- Master-Reset (ativo em LOW)
        pc_count    : out std_logic_vector(n-1 downto 0);     -- Program Count
        inst_out    : out std_logic_vector(i_word-1 downto 0) -- Leitura do IR
    );

  end component cpu;

begin

    -- Instanciando o BIP (do tipo cpu) e declarando as portas:

    BIP: cpu port map (enable_clk, MR, pc_count, inst_out);

    -- Testando o Program Counter (PC) do BIP:

    test: process
    begin

        MR <= '0';
        wait for 1 ns;
        MR <= '1';
        wait for 7 ns;
        MR <= '0';
        wait for 1 ns;
        MR <= '1';
        wait for 30 ns;
        enable_clk <= '0';

        wait;

    end process test;

end architecture teste;

test/waveform/cpu_tb.vcd
$date
  Sun Jun 23 22:00:08 2024
$end
$version
  GHDL v0
$end
$timescale
  1 fs
$end
$scope module standard $end
$upscope $end
$scope module textio $end
$upscope $end
$scope module std_logic_1164 $end
$upscope $end
$scope module numeric_std $end
$upscope $end
$scope module cpu_tb $end
$var reg 1 ! enable_clk $end
$var reg 1 " mr $end
$var reg 16 # pc_count[15:0] $end
$var reg 16 $ inst_out[15:0] $end
$scope module bip $end
$var reg 1 % enable_clk $end
$var reg 1 & mr $end
$var reg 16 ' pc_count[15:0] $end
$var reg 16 ( inst_out[15:0] $end
$var reg 1 ) internal_clk $end
$var reg 16 * instruction[15:0] $end
$var reg 1 + wr_ir $end
$scope module timer $end
$var reg 1 , clk $end
$var reg 1 - enable $end
$upscope $end
$scope module pc_counter $end
$var reg 1 . clk $end
$var reg 1 / mr $end
$var reg 16 0 count[15:0] $end
$var reg 16 1 count_temp[15:0] $end
$upscope $end
$scope module rom $end
$var reg 1 2 cs $end
$var reg 1 3 oe $end
$var reg 16 4 address[15:0] $end
$var reg 16 5 data_out[15:0] $end
$upscope $end
$scope module ir $end
$var reg 16 6 data_in[15:0] $end
$var reg 1 7 enable $end
$var reg 1 8 mr $end
$var reg 1 9 clk $end
$var reg 16 : data_out[15:0] $end
$upscope $end
$upscope $end
$upscope $end
$enddefinitions $end
#0
1!
0"
b0000000000000000 #
b0000000000000000 $
1%
0&
b0000000000000000 '
b0000000000000000 (
1)
b1010101010101010 *
1+
1,
1-
1.
0/
b0000000000000000 0
b0000000000000000 1
02
03
b0000000000000000 4
b1010101010101010 5
b1010101010101010 6
17
08
19
b0000000000000000 :
#500000
0)
0,
0.
09
#1000000
1"
1&
1)
1,
1.
1/
18
19
#1500000
b0000000000000001 #
b1010101010101010 $
b0000000000000001 '
b1010101010101010 (
0)
b1011101110111011 *
0,
0.
b0000000000000001 0
b0000000000000001 1
b0000000000000001 4
b1011101110111011 5
b1011101110111011 6
09
b1010101010101010 :
#2000000
1)
1,
1.
19
#2500000
b0000000000000010 #
b1011101110111011 $
b0000000000000010 '
b1011101110111011 (
0)
b1100110011001100 *
0,
0.
b0000000000000010 0
b0000000000000010 1
b0000000000000010 4
b1100110011001100 5
b1100110011001100 6
09
b1011101110111011 :
#3000000
1)
1,
1.
19
#3500000
b0000000000000011 #
b1100110011001100 $
b0000000000000011 '
b1100110011001100 (
0)
b1101110111011101 *
0,
0.
b0000000000000011 0
b0000000000000011 1
b0000000000000011 4
b1101110111011101 5
b1101110111011101 6
09
b1100110011001100 :
#4000000
1)
1,
1.
19
#4500000
b0000000000000100 #
b1101110111011101 $
b0000000000000100 '
b1101110111011101 (
0)
b0000000000000000 *
0,
0.
b0000000000000100 0
b0000000000000100 1
b0000000000000100 4
b0000000000000000 5
b0000000000000000 6
09
b1101110111011101 :
#5000000
1)
1,
1.
19
#5500000
b0000000000000101 #
b0000000000000000 $
b0000000000000101 '
b0000000000000000 (
0)
0,
0.
b0000000000000101 0
b0000000000000101 1
b0000000000000101 4
09
b0000000000000000 :
#6000000
1)
1,
1.
19
#6500000
b0000000000000110 #
b0000000000000110 '
0)
0,
0.
b0000000000000110 0
b0000000000000110 1
b0000000000000110 4
09
#7000000
1)
1,
1.
19
#7500000
b0000000000000111 #
b0000000000000111 '
0)
0,
0.
b0000000000000111 0
b0000000000000111 1
b0000000000000111 4
09
#8000000
0"
b0000000000000000 #
0&
b0000000000000000 '
1)
b1010101010101010 *
1,
1.
0/
b0000000000000000 0
b0000000000000000 1
b0000000000000000 4
b1010101010101010 5
b1010101010101010 6
08
19
#8500000
0)
0,
0.
09
#9000000
1"
1&
1)
1,
1.
1/
18
19
#9500000
b0000000000000001 #
b1010101010101010 $
b0000000000000001 '
b1010101010101010 (
0)
b1011101110111011 *
0,
0.
b0000000000000001 0
b0000000000000001 1
b0000000000000001 4
b1011101110111011 5
b1011101110111011 6
09
b1010101010101010 :
#10000000
1)
1,
1.
19
#10500000
b0000000000000010 #
b1011101110111011 $
b0000000000000010 '
b1011101110111011 (
0)
b1100110011001100 *
0,
0.
b0000000000000010 0
b0000000000000010 1
b0000000000000010 4
b1100110011001100 5
b1100110011001100 6
09
b1011101110111011 :
#11000000
1)
1,
1.
19
#11500000
b0000000000000011 #
b1100110011001100 $
b0000000000000011 '
b1100110011001100 (
0)
b1101110111011101 *
0,
0.
b0000000000000011 0
b0000000000000011 1
b0000000000000011 4
b1101110111011101 5
b1101110111011101 6
09
b1100110011001100 :
#12000000
1)
1,
1.
19
#12500000
b0000000000000100 #
b1101110111011101 $
b0000000000000100 '
b1101110111011101 (
0)
b0000000000000000 *
0,
0.
b0000000000000100 0
b0000000000000100 1
b0000000000000100 4
b0000000000000000 5
b0000000000000000 6
09
b1101110111011101 :
#13000000
1)
1,
1.
19
#13500000
b0000000000000101 #
b0000000000000000 $
b0000000000000101 '
b0000000000000000 (
0)
0,
0.
b0000000000000101 0
b0000000000000101 1
b0000000000000101 4
09
b0000000000000000 :
#14000000
1)
1,
1.
19
#14500000
b0000000000000110 #
b0000000000000110 '
0)
0,
0.
b0000000000000110 0
b0000000000000110 1
b0000000000000110 4
09
#15000000
1)
1,
1.
19
#15500000
b0000000000000111 #
b0000000000000111 '
0)
0,
0.
b0000000000000111 0
b0000000000000111 1
b0000000000000111 4
09
#16000000
1)
1,
1.
19
#16500000
b0000000000001000 #
b0000000000001000 '
0)
0,
0.
b0000000000001000 0
b0000000000001000 1
b0000000000001000 4
09
#17000000
1)
1,
1.
19
#17500000
b0000000000001001 #
b0000000000001001 '
0)
0,
0.
b0000000000001001 0
b0000000000001001 1
b0000000000001001 4
09
#18000000
1)
1,
1.
19
#18500000
b0000000000001010 #
b0000000000001010 '
0)
0,
0.
b0000000000001010 0
b0000000000001010 1
b0000000000001010 4
09
#19000000
1)
1,
1.
19
#19500000
b0000000000001011 #
b0000000000001011 '
0)
0,
0.
b0000000000001011 0
b0000000000001011 1
b0000000000001011 4
09
#20000000
1)
1,
1.
19
#20500000
b0000000000001100 #
b0000000000001100 '
0)
0,
0.
b0000000000001100 0
b0000000000001100 1
b0000000000001100 4
09
#21000000
1)
1,
1.
19
#21500000
b0000000000001101 #
b0000000000001101 '
0)
0,
0.
b0000000000001101 0
b0000000000001101 1
b0000000000001101 4
09
#22000000
1)
1,
1.
19
#22500000
b0000000000001110 #
b0000000000001110 '
0)
0,
0.
b0000000000001110 0
b0000000000001110 1
b0000000000001110 4
09
#23000000
1)
1,
1.
19
#23500000
b0000000000001111 #
b0000000000001111 '
0)
0,
0.
b0000000000001111 0
b0000000000001111 1
b0000000000001111 4
09
#24000000
1)
1,
1.
19
#24500000
b0000000000010000 #
b0000000000010000 '
0)
0,
0.
b0000000000010000 0
b0000000000010000 1
b0000000000010000 4
09
#25000000
1)
1,
1.
19
#25500000
b0000000000010001 #
b0000000000010001 '
0)
0,
0.
b0000000000010001 0
b0000000000010001 1
b0000000000010001 4
09
#26000000
1)
1,
1.
19
#26500000
b0000000000010010 #
b0000000000010010 '
0)
0,
0.
b0000000000010010 0
b0000000000010010 1
b0000000000010010 4
09
#27000000
1)
1,
1.
19
#27500000
b0000000000010011 #
b0000000000010011 '
0)
0,
0.
b0000000000010011 0
b0000000000010011 1
b0000000000010011 4
09
#28000000
1)
1,
1.
19
#28500000
b0000000000010100 #
b0000000000010100 '
0)
0,
0.
b0000000000010100 0
b0000000000010100 1
b0000000000010100 4
09
#29000000
1)
1,
1.
19
#29500000
b0000000000010101 #
b0000000000010101 '
0)
0,
0.
b0000000000010101 0
b0000000000010101 1
b0000000000010101 4
09
#30000000
1)
1,
1.
19
#30500000
b0000000000010110 #
b0000000000010110 '
0)
0,
0.
b0000000000010110 0
b0000000000010110 1
b0000000000010110 4
09
#31000000
1)
1,
1.
19
#31500000
b0000000000010111 #
b0000000000010111 '
0)
0,
0.
b0000000000010111 0
b0000000000010111 1
b0000000000010111 4
09
#32000000
1)
1,
1.
19
#32500000
b0000000000011000 #
b0000000000011000 '
0)
0,
0.
b0000000000011000 0
b0000000000011000 1
b0000000000011000 4
09
#33000000
1)
1,
1.
19
#33500000
b0000000000011001 #
b0000000000011001 '
0)
0,
0.
b0000000000011001 0
b0000000000011001 1
b0000000000011001 4
09
#34000000
1)
1,
1.
19
#34500000
b0000000000011010 #
b0000000000011010 '
0)
0,
0.
b0000000000011010 0
b0000000000011010 1
b0000000000011010 4
09
#35000000
1)
1,
1.
19
#35500000
b0000000000011011 #
b0000000000011011 '
0)
0,
0.
b0000000000011011 0
b0000000000011011 1
b0000000000011011 4
09
#36000000
1)
1,
1.
19
#36500000
b0000000000011100 #
b0000000000011100 '
0)
0,
0.
b0000000000011100 0
b0000000000011100 1
b0000000000011100 4
09
#37000000
1)
1,
1.
19
#37500000
b0000000000011101 #
b0000000000011101 '
0)
0,
0.
b0000000000011101 0
b0000000000011101 1
b0000000000011101 4
09
#38000000
1)
1,
1.
19
#38500000
b0000000000011110 #
b0000000000011110 '
0)
0,
0.
b0000000000011110 0
b0000000000011110 1
b0000000000011110 4
09
#39000000
0!
0%
1)
1,
0-
1.
19
#39500000
b0000000000011111 #
b0000000000011111 '
0)
0,
0.
b0000000000011111 0
b0000000000011111 1
b0000000000011111 4
09
