src/components/counter/generic_counter.vhd
-- Descrição de Hardware (VHDL) de um Contador Genérico de n bits
--
--                  __________
--          clk >--|          |
--                 | Contador |--> count (n bits) 
--           MR >--|__________|
--
--
-- AUTOR: André Solano F. R. Maiolini
-- DATA: 23/06/2024

--| Libraries |------------------------------------------------------------------------------

library ieee;
use ieee.std_logic_1164.all;
use ieee.numeric_std.all;

--| Contador |--------------------------------------------------------------------------------

entity generic_counter is
    generic(n : integer := 4); -- quantidade de bits do contador
    port (
        clk    : in  std_logic;
        MR     : in  std_logic;
        count  : out std_logic_vector(n - 1 downto 0)
    );
end entity generic_counter;

--| Lógica |----------------------------------------------------------------------------------

architecture main of generic_counter is

    signal count_temp : unsigned(n-1 downto 0);

begin

    contagem : process(clk, MR) 
    begin

        if MR = '0' then

            count_temp <= (others => '0');

        elsif falling_edge(clk) then

            count_temp <= count_temp + 1;

        end if;

    end process contagem;

    count <= std_logic_vector(count_temp);

end architecture main;

src/components/timer/generic_timer.vhd
-- Descrição de Hardware (VHDL) de um Timer de Freq. Genérica (MHz)
--
--             _________
--            |         |
--      en >--|  Timer  |--> clk
--            |_________|
--
--
-- AUTOR: André Solano F. R. Maiolini
-- DATA: 23/06/2024

--| Libraries |------------------------------------------------------------------------------

library ieee;
use ieee.std_logic_1164.all;
use ieee.numeric_std.all;

--| Timer |----------------------------------------------------------------------------------

entity generic_timer is

    generic(
        clk_freq : integer := 4
    );

    port(
        clk : out std_logic := '0';
        enable : in std_logic
    );

end entity generic_timer;

--| Lógica |----------------------------------------------------------------------------------

architecture main of generic_timer is
begin

    clock_generator : process
    begin
        
        while enable = '1' loop
            clk <= not clk;
            wait for (1000 ns / clk_freq);
        end loop;
        
        clk <= '0';

        wait;

    end process;

end architecture main;

src/cpu.vhd
--| Libraries |------------------------------------------------------------------------------
library ieee;
use ieee.std_logic_1164.all;
use ieee.numeric_std.all;

--| CPU |------------------------------------------------------------------------------------

entity cpu is

    -- Define genericamente os valores que serão fornecidos pelo arquivo de testes:

    generic(
        n : integer := 16;                                -- Tamanho em bits do PC
        f : integer := 2000                               -- MHz (freq. clock)
    );

    -- Define as portas da CPU - entradas, saídas e tipos básicos:

    port(
        enable    : in  std_logic;                        -- Enable (ativo em HIGH)
        MR        : in  std_logic;                        -- Master-Reset (ativo em LOW)
        pc_count  : out std_logic_vector(n-1 downto 0)    -- Program Counter (PC)
    );

end entity cpu;

--| Lógica |----------------------------------------------------------------------------------

architecture main of cpu is

    -- Definindo sinais internos à CPU:

    signal internal_clk : std_logic;         -- Clock interno da CPU (recebe o clock do TIMER)

    -- Definindo os componentes internos da CPU:

        -- Temporizador genérico:

        component generic_timer is
            generic(
                clk_freq : integer := f      -- Define a frequência do temporizador
            );
            port(
                clk : out std_logic := '0';
                enable : in std_logic
            );
        end component generic_timer;

        -- Contador genérico:

        component generic_counter is
            generic(
                n : integer := n             -- Define a largura de bits do contador
            );
            port (
                clk    : in  std_logic;
                MR     : in  std_logic;
                count  : out std_logic_vector(n - 1 downto 0)
            );
        end component generic_counter;

begin

    -- Instância o relógio interno da CPU: TIMER

    TIMER: generic_timer 
        port map(
            internal_clk,                    -- Recebe, a partir do TIMER o internal_clock
            enable                           -- Sinal para habilitar o TIMER interno da CPU
        );

    -- Instância o circuito Program Counter: PC_counter

    PC_counter: generic_counter
        port map(
            internal_clk,                    -- Atribui o clock interno da CPU para o contador
            MR,                              -- Sinal de Master-Reset do PC_counter
            pc_count                         -- Direciona o valor do PC para pc_count
        );

end architecture main;

----------------------------------------------------------------------------------------------

test/testbench/cpu_tb.vhd
-- Arquivo de testes (testbench) para a CPU (BIP I)

--| Libraries |----------------------------------------------------------------------------------------------------------

library ieee;
use ieee.std_logic_1164.all;

--| Entidade |-----------------------------------------------------------------------------------------------------------

entity cpu_tb is
end entity cpu_tb;

--| Lógica - Testbench |-------------------------------------------------------------------------------------------------

architecture teste of cpu_tb is
  
  -- Definições básicas do processador:

  constant n : integer := 16;                               -- Tamanho do Program Counter (PC) da CPU em bits
  constant f : integer := 2000;                             -- Frequência de operação do Timer Interno (MHz)
  
  -- Sinais sendo rastreados:

  signal enable   : std_logic := '1';                       -- Enable (ativo em HIGH)
  signal MR       : std_logic;                              -- Master-Reset (ativo em LOW)
  signal pc_count : std_logic_vector(n-1 downto 0);         -- Program Count

  -- Declaração do componente CPU:

  component cpu is

    generic(
        n : integer := n;
        f : integer := f
    );

    port(
        enable    : in  std_logic;                          -- Enable (ativo em HIGH)
        MR        : in  std_logic;                          -- Master-Reset (ativo em LOW)
        pc_count  : out std_logic_vector(n-1 downto 0)      -- Program Count
    );

  end component cpu;

begin

    -- Instanciando o BIP (do tipo cpu) e declarando as portas:

    BIP: cpu port map (enable, MR, pc_count);

    -- Testando o Program Counter (PC) do BIP:

    test: process
    begin

        MR <= '0';
        wait for 1 ns;
        MR <= '1';
        wait for 7 ns;
        MR <= '0';
        wait for 1 ns;
        MR <= '1';
        wait for 30 ns;
        enable <= '0';

        wait;

    end process test;

end architecture teste;

test/waveform/cpu_tb.vcd
$date
  Sun Jun 23 20:31:36 2024
$end
$version
  GHDL v0
$end
$timescale
  1 fs
$end
$scope module standard $end
$upscope $end
$scope module textio $end
$upscope $end
$scope module std_logic_1164 $end
$upscope $end
$scope module numeric_std $end
$upscope $end
$scope module cpu_tb $end
$var reg 1 ! enable $end
$var reg 1 " mr $end
$var reg 16 # pc_count[15:0] $end
$scope module bip $end
$var reg 1 $ enable $end
$var reg 1 % mr $end
$var reg 16 & pc_count[15:0] $end
$var reg 1 ' internal_clk $end
$scope module timer $end
$var reg 1 ( clk $end
$var reg 1 ) enable $end
$upscope $end
$scope module pc_counter $end
$var reg 1 * clk $end
$var reg 1 + mr $end
$var reg 16 , count[15:0] $end
$var reg 16 - count_temp[15:0] $end
$upscope $end
$upscope $end
$upscope $end
$enddefinitions $end
#0
1!
0"
b0000000000000000 #
1$
0%
b0000000000000000 &
1'
1(
1)
1*
0+
b0000000000000000 ,
b0000000000000000 -
#500000
0'
0(
0*
#1000000
1"
1%
1'
1(
1*
1+
#1500000
b0000000000000001 #
b0000000000000001 &
0'
0(
0*
b0000000000000001 ,
b0000000000000001 -
#2000000
1'
1(
1*
#2500000
b0000000000000010 #
b0000000000000010 &
0'
0(
0*
b0000000000000010 ,
b0000000000000010 -
#3000000
1'
1(
1*
#3500000
b0000000000000011 #
b0000000000000011 &
0'
0(
0*
b0000000000000011 ,
b0000000000000011 -
#4000000
1'
1(
1*
#4500000
b0000000000000100 #
b0000000000000100 &
0'
0(
0*
b0000000000000100 ,
b0000000000000100 -
#5000000
1'
1(
1*
#5500000
b0000000000000101 #
b0000000000000101 &
0'
0(
0*
b0000000000000101 ,
b0000000000000101 -
#6000000
1'
1(
1*
#6500000
b0000000000000110 #
b0000000000000110 &
0'
0(
0*
b0000000000000110 ,
b0000000000000110 -
#7000000
1'
1(
1*
#7500000
b0000000000000111 #
b0000000000000111 &
0'
0(
0*
b0000000000000111 ,
b0000000000000111 -
#8000000
0"
b0000000000000000 #
0%
b0000000000000000 &
1'
1(
1*
0+
b0000000000000000 ,
b0000000000000000 -
#8500000
0'
0(
0*
#9000000
1"
1%
1'
1(
1*
1+
#9500000
b0000000000000001 #
b0000000000000001 &
0'
0(
0*
b0000000000000001 ,
b0000000000000001 -
#10000000
1'
1(
1*
#10500000
b0000000000000010 #
b0000000000000010 &
0'
0(
0*
b0000000000000010 ,
b0000000000000010 -
#11000000
1'
1(
1*
#11500000
b0000000000000011 #
b0000000000000011 &
0'
0(
0*
b0000000000000011 ,
b0000000000000011 -
#12000000
1'
1(
1*
#12500000
b0000000000000100 #
b0000000000000100 &
0'
0(
0*
b0000000000000100 ,
b0000000000000100 -
#13000000
1'
1(
1*
#13500000
b0000000000000101 #
b0000000000000101 &
0'
0(
0*
b0000000000000101 ,
b0000000000000101 -
#14000000
1'
1(
1*
#14500000
b0000000000000110 #
b0000000000000110 &
0'
0(
0*
b0000000000000110 ,
b0000000000000110 -
#15000000
1'
1(
1*
#15500000
b0000000000000111 #
b0000000000000111 &
0'
0(
0*
b0000000000000111 ,
b0000000000000111 -
#16000000
1'
1(
1*
#16500000
b0000000000001000 #
b0000000000001000 &
0'
0(
0*
b0000000000001000 ,
b0000000000001000 -
#17000000
1'
1(
1*
#17500000
b0000000000001001 #
b0000000000001001 &
0'
0(
0*
b0000000000001001 ,
b0000000000001001 -
#18000000
1'
1(
1*
#18500000
b0000000000001010 #
b0000000000001010 &
0'
0(
0*
b0000000000001010 ,
b0000000000001010 -
#19000000
1'
1(
1*
#19500000
b0000000000001011 #
b0000000000001011 &
0'
0(
0*
b0000000000001011 ,
b0000000000001011 -
#20000000
1'
1(
1*
#20500000
b0000000000001100 #
b0000000000001100 &
0'
0(
0*
b0000000000001100 ,
b0000000000001100 -
#21000000
1'
1(
1*
#21500000
b0000000000001101 #
b0000000000001101 &
0'
0(
0*
b0000000000001101 ,
b0000000000001101 -
#22000000
1'
1(
1*
#22500000
b0000000000001110 #
b0000000000001110 &
0'
0(
0*
b0000000000001110 ,
b0000000000001110 -
#23000000
1'
1(
1*
#23500000
b0000000000001111 #
b0000000000001111 &
0'
0(
0*
b0000000000001111 ,
b0000000000001111 -
#24000000
1'
1(
1*
#24500000
b0000000000010000 #
b0000000000010000 &
0'
0(
0*
b0000000000010000 ,
b0000000000010000 -
#25000000
1'
1(
1*
#25500000
b0000000000010001 #
b0000000000010001 &
0'
0(
0*
b0000000000010001 ,
b0000000000010001 -
#26000000
1'
1(
1*
#26500000
b0000000000010010 #
b0000000000010010 &
0'
0(
0*
b0000000000010010 ,
b0000000000010010 -
#27000000
1'
1(
1*
#27500000
b0000000000010011 #
b0000000000010011 &
0'
0(
0*
b0000000000010011 ,
b0000000000010011 -
#28000000
1'
1(
1*
#28500000
b0000000000010100 #
b0000000000010100 &
0'
0(
0*
b0000000000010100 ,
b0000000000010100 -
#29000000
1'
1(
1*
#29500000
b0000000000010101 #
b0000000000010101 &
0'
0(
0*
b0000000000010101 ,
b0000000000010101 -
#30000000
1'
1(
1*
#30500000
b0000000000010110 #
b0000000000010110 &
0'
0(
0*
b0000000000010110 ,
b0000000000010110 -
#31000000
1'
1(
1*
#31500000
b0000000000010111 #
b0000000000010111 &
0'
0(
0*
b0000000000010111 ,
b0000000000010111 -
#32000000
1'
1(
1*
#32500000
b0000000000011000 #
b0000000000011000 &
0'
0(
0*
b0000000000011000 ,
b0000000000011000 -
#33000000
1'
1(
1*
#33500000
b0000000000011001 #
b0000000000011001 &
0'
0(
0*
b0000000000011001 ,
b0000000000011001 -
#34000000
1'
1(
1*
#34500000
b0000000000011010 #
b0000000000011010 &
0'
0(
0*
b0000000000011010 ,
b0000000000011010 -
#35000000
1'
1(
1*
#35500000
b0000000000011011 #
b0000000000011011 &
0'
0(
0*
b0000000000011011 ,
b0000000000011011 -
#36000000
1'
1(
1*
#36500000
b0000000000011100 #
b0000000000011100 &
0'
0(
0*
b0000000000011100 ,
b0000000000011100 -
#37000000
1'
1(
1*
#37500000
b0000000000011101 #
b0000000000011101 &
0'
0(
0*
b0000000000011101 ,
b0000000000011101 -
#38000000
1'
1(
1*
#38500000
b0000000000011110 #
b0000000000011110 &
0'
0(
0*
b0000000000011110 ,
b0000000000011110 -
#39000000
0!
0$
1'
1(
0)
1*
#39500000
b0000000000011111 #
b0000000000011111 &
0'
0(
0*
b0000000000011111 ,
b0000000000011111 -
